huddle/__init__.py
huddle/__main__.py
huddle/manage.py
huddle/repo.py
huddle/util.py
huddle/version.py
huddle-0.1.5.dist-info/DESCRIPTION.rst
huddle-0.1.5.dist-info/METADATA
huddle-0.1.5.dist-info/RECORD
huddle-0.1.5.dist-info/WHEEL
huddle-0.1.5.dist-info/entry_points.txt
huddle-0.1.5.dist-info/metadata.json
huddle-0.1.5.dist-info/top_level.txt
