Metadata-Version: 2.0
Name: huddle
Version: 0.1.5
Summary: A server-oriented auto-deployment utility for any type of program or script
Home-page: https://github.com/slightlynybbled/huddle
Author: Jason Jones
Author-email: slightlynybbled@gmail.com
License: UNKNOWN
Keywords: auto-deployment,huddle
Platform: UNKNOWN
Classifier: Development Status :: 3 - Alpha
Classifier: Environment :: Console
Classifier: Intended Audience :: Developers
Classifier: Intended Audience :: System Administrators
Classifier: License :: CC0 1.0 Universal (CC0 1.0) Public Domain Dedication
Classifier: Natural Language :: English
Classifier: Operating System :: POSIX :: Linux
Classifier: Operating System :: Microsoft :: Windows
Classifier: Programming Language :: Python :: 3
Classifier: Programming Language :: Python :: 3.3
Classifier: Programming Language :: Python :: 3.4
Classifier: Programming Language :: Python :: 3.5
Classifier: Programming Language :: Python :: 3.6
Classifier: Topic :: System :: Software Distribution
Classifier: Topic :: Utilities
Requires-Dist: requests (>=2.12.4)
